loadTDT/__init__.py
loadTDT/loadTDT.py
loadTDT/test.py
loadTDT/test_new.py
loadTDT-0.1.1.dist-info/METADATA
loadTDT-0.1.1.dist-info/RECORD
loadTDT-0.1.1.dist-info/WHEEL
loadTDT-0.1.1.dist-info/top_level.txt
