Metadata-Version: 2.1
Name: loadTDT
Version: 0.1.1
Summary: Read a TDT tank into a python dictionary
Home-page: https://github.com/logangrado/loadTDT
Author: Logan Grado
Author-email: grado@umn.edu
License: GNU GPLv3
Platform: UNKNOWN
Requires-Dist: numpy
